odoo10_addon_web_ir_actions_act_window_message-10.0.1.0.0-py2.7-nspkg.pth
odoo/addons/web_ir_actions_act_window_message/README.rst
odoo/addons/web_ir_actions_act_window_message/__init__.py
odoo/addons/web_ir_actions_act_window_message/__manifest__.py
odoo/addons/web_ir_actions_act_window_message/i18n/ar.po
odoo/addons/web_ir_actions_act_window_message/i18n/de.po
odoo/addons/web_ir_actions_act_window_message/i18n/es.po
odoo/addons/web_ir_actions_act_window_message/i18n/eu.po
odoo/addons/web_ir_actions_act_window_message/i18n/fi.po
odoo/addons/web_ir_actions_act_window_message/i18n/fr.po
odoo/addons/web_ir_actions_act_window_message/i18n/hr.po
odoo/addons/web_ir_actions_act_window_message/i18n/it.po
odoo/addons/web_ir_actions_act_window_message/i18n/nl.po
odoo/addons/web_ir_actions_act_window_message/i18n/pt_BR.po
odoo/addons/web_ir_actions_act_window_message/i18n/sl.po
odoo/addons/web_ir_actions_act_window_message/i18n/tr.po
odoo/addons/web_ir_actions_act_window_message/static/description/icon.png
odoo/addons/web_ir_actions_act_window_message/static/src/js/web_ir_actions_act_window_message.js
odoo/addons/web_ir_actions_act_window_message/static/src/xml/web_ir_actions_act_window_message.xml
odoo/addons/web_ir_actions_act_window_message/views/templates.xml
odoo10_addon_web_ir_actions_act_window_message-10.0.1.0.0.dist-info/DESCRIPTION.rst
odoo10_addon_web_ir_actions_act_window_message-10.0.1.0.0.dist-info/METADATA
odoo10_addon_web_ir_actions_act_window_message-10.0.1.0.0.dist-info/RECORD
odoo10_addon_web_ir_actions_act_window_message-10.0.1.0.0.dist-info/WHEEL
odoo10_addon_web_ir_actions_act_window_message-10.0.1.0.0.dist-info/metadata.json
odoo10_addon_web_ir_actions_act_window_message-10.0.1.0.0.dist-info/namespace_packages.txt
odoo10_addon_web_ir_actions_act_window_message-10.0.1.0.0.dist-info/top_level.txt
